pyatcommand/__init__.py
pyatcommand/client.py
pyatcommand/common.py
pyatcommand/crcxmodem.py
pyatcommand/exception.py
pyatcommand/remote.py
pyatcommand/server.py
pyatcommand/xmodem.py
pyatcommand-0.5.3.dist-info/LICENSE
pyatcommand-0.5.3.dist-info/METADATA
pyatcommand-0.5.3.dist-info/WHEEL
pyatcommand-0.5.3.dist-info/RECORD
