Metadata-Version: 2.1
Name: pyatcommand
Version: 0.5.3
Summary: An interface for V.25 Hayes AT commands
Home-page: https://github.com/gbrucepayne/pyatcommand
License: MIT
Author: gbrucepayne
Author-email: gbrucepayne@hotmail.com
Requires-Python: >=3.9,<4.0
Classifier: License :: OSI Approved :: MIT License
Classifier: Programming Language :: Python :: 3
Classifier: Programming Language :: Python :: 3.9
Classifier: Programming Language :: Python :: 3.10
Classifier: Programming Language :: Python :: 3.11
Classifier: Programming Language :: Python :: 3.12
Requires-Dist: pyserial (>=3.5,<4.0)
Requires-Dist: pyserial-asyncio (>=0.6,<0.7)
Requires-Dist: python-dotenv (>=1.0.1,<2.0.0)
Requires-Dist: xmodem (>=0.4.7,<0.5.0)
Project-URL: Repository, https://github.com/gbrucepayne/pyatcommand
